{
  ":p": {
    "builtins": {
      ":preferences": [
        1732504331
      ]
    }
  },
  ":pr": {
    "builtins": {
      ":preferences": [
        1732504331
      ]
    }
  },
  ":pre": {
    "builtins": {
      ":preferences": [
        1732504331
      ]
    }
  },
  ":pref": {
    "builtins": {
      ":preferences": [
        1732504331
      ]
    }
  },
  "a": {
    "apps": {
      "mpv.desktop": [
        1733200832
      ]
    }
  },
  "au": {
    "apps": {
      "mpv.desktop": [
        1733200832
      ]
    }
  },
  "b": {
    "apps": {
      "btop.desktop": [
        1731526679
      ]
    }
  },
  "bt": {
    "apps": {
      "btop.desktop": [
        1731526679
      ]
    }
  },
  "c": {
    "apps": {
      "FRC VS Code 2024.desktop": [
        1733449332
      ],
      "org.gnome.Calculator.desktop": [
        1731470753,
        1731472367,
        1731651693,
        1732252880,
        1732943831
      ],
      "org.gnome.Calendar.desktop": [
        1732158848,
        1732252884,
        1732943834
      ]
    }
  },
  "ca": {
    "apps": {
      "org.gnome.Calculator.desktop": [
        1731466923,
        1731472367,
        1731651693,
        1732252880,
        1732943831
      ],
      "org.gnome.Calendar.desktop": [
        1732158848,
        1732252884,
        1732943834
      ]
    }
  },
  "cal": {
    "apps": {
      "org.gnome.Calculator.desktop": [
        1731466923,
        1731472367,
        1731651693,
        1732252880,
        1732943831
      ],
      "org.gnome.Calendar.desktop": [
        1732158848,
        1732252884,
        1732943834
      ]
    }
  },
  "calc": {
    "apps": {
      "org.gnome.Calculator.desktop": [
        1731466923,
        1731651693
      ]
    }
  },
  "co": {
    "apps": {
      "FRC VS Code 2024.desktop": [
        1733449332
      ]
    }
  },
  "d": {
    "apps": {
      "avahi-discover.desktop": [
        1733645198
      ],
      "discord.desktop": [
        1731453745,
        1731453830,
        1731454951,
        1731457034,
        1731466566
      ],
      "org.gnome.DiskUtility.desktop": [
        1732159743,
        1732336596,
        1733645195,
        1733793638,
        1733868103
      ]
    }
  },
  "di": {
    "apps": {
      "avahi-discover.desktop": [
        1733645198
      ],
      "discord.desktop": [
        1731453745,
        1731453830,
        1731454951,
        1731457034,
        1731466566
      ],
      "org.gnome.DiskUtility.desktop": [
        1732159743,
        1732336596,
        1733645195,
        1733793638,
        1733868103
      ]
    }
  },
  "dis": {
    "apps": {
      "avahi-discover.desktop": [
        1733645198
      ],
      "discord.desktop": [
        1731453745,
        1731453830,
        1731454951,
        1731457034,
        1731466566
      ],
      "org.gnome.DiskUtility.desktop": [
        1732159743,
        1732336596,
        1733645195,
        1733793638,
        1733868103
      ]
    }
  },
  "disc": {
    "apps": {
      "avahi-discover.desktop": [
        1733645198
      ]
    }
  },
  "disk": {
    "apps": {
      "org.gnome.DiskUtility.desktop": [
        1731881978
      ]
    }
  },
  "e": {
    "apps": {
      "org.gnome.Evince.desktop": [
        1731895144
      ]
    }
  },
  "ev": {
    "apps": {
      "org.gnome.Evince.desktop": [
        1731895144
      ]
    }
  },
  "evi": {
    "apps": {
      "org.gnome.Evince.desktop": [
        1731895144
      ]
    }
  },
  "f": {
    "apps": {
      "com.github.FontManager.FontManager.desktop": [
        1731967988,
        1731968027
      ],
      "com.github.FontManager.FontViewer.desktop": [
        1731968020,
        1731968024
      ],
      "firefox.desktop": [
        1733879329,
        1733900835,
        1733940006,
        1733944416,
        1733945443
      ],
      "org.gnome.Nautilus.desktop": [
        1733729489,
        1733730936,
        1733792326,
        1733868779,
        1733900842
      ]
    }
  },
  "fi": {
    "apps": {
      "firefox.desktop": [
        1733879329,
        1733900835,
        1733940006,
        1733944416,
        1733945443
      ],
      "org.gnome.Nautilus.desktop": [
        1733729489,
        1733730936,
        1733792326,
        1733868779,
        1733900842
      ]
    }
  },
  "fil": {
    "apps": {
      "org.gnome.Nautilus.desktop": [
        1733729489,
        1733730936,
        1733792326,
        1733868779,
        1733900842
      ]
    }
  },
  "file": {
    "apps": {
      "org.gnome.Nautilus.desktop": [
        1733729489,
        1733730936,
        1733792326,
        1733868779,
        1733900842
      ]
    }
  },
  "fir": {
    "apps": {
      "firefox.desktop": [
        1733879329,
        1733900835,
        1733940006,
        1733944416,
        1733945443
      ]
    }
  },
  "fire": {
    "apps": {
      "firefox.desktop": [
        1733879329,
        1733900835,
        1733940006,
        1733944416,
        1733945443
      ]
    }
  },
  "fo": {
    "apps": {
      "com.github.FontManager.FontManager.desktop": [
        1731967988,
        1731968027
      ],
      "com.github.FontManager.FontViewer.desktop": [
        1731968020,
        1731968024
      ]
    }
  },
  "fon": {
    "apps": {
      "com.github.FontManager.FontManager.desktop": [
        1731967988,
        1731968027
      ],
      "com.github.FontManager.FontViewer.desktop": [
        1731968020,
        1731968024
      ]
    }
  },
  "font": {
    "apps": {
      "com.github.FontManager.FontManager.desktop": [
        1731968027
      ]
    }
  },
  "g": {
    "apps": {
      "com.github.GradienceTeam.Gradience.desktop": [
        1733162515
      ]
    }
  },
  "gr": {
    "apps": {
      "com.github.GradienceTeam.Gradience.desktop": [
        1733162515
      ]
    }
  },
  "gra": {
    "apps": {
      "com.github.GradienceTeam.Gradience.desktop": [
        1733162515
      ]
    }
  },
  "grad": {
    "apps": {
      "com.github.GradienceTeam.Gradience.desktop": [
        1733162515
      ]
    }
  },
  "h": {
    "apps": {
      "helix.desktop": [
        1733353387,
        1733353394,
        1733422964,
        1733448101,
        1733871011
      ],
      "jshell-java17-openjdk.desktop": [
        1731697176
      ]
    }
  },
  "he": {
    "apps": {
      "helix.desktop": [
        1733353387,
        1733353394,
        1733422964,
        1733448101,
        1733871011
      ],
      "jshell-java17-openjdk.desktop": [
        1731697176
      ]
    }
  },
  "hel": {
    "apps": {
      "helix.desktop": [
        1733353387,
        1733353394,
        1733422964,
        1733448101,
        1733871011
      ]
    }
  },
  "heli": {
    "apps": {
      "helix.desktop": [
        1733334493,
        1733353387,
        1733353394,
        1733448101,
        1733871011
      ]
    }
  },
  "i": {
    "apps": {
      "idea.desktop": [
        1731977466
      ]
    }
  },
  "id": {
    "apps": {
      "idea.desktop": [
        1731977466
      ]
    }
  },
  "ide": {
    "apps": {
      "idea.desktop": [
        1731977466
      ]
    }
  },
  "idea": {
    "apps": {
      "idea.desktop": [
        1731977466
      ]
    }
  },
  "j": {
    "apps": {
      "joshuto.desktop": [
        1731697796,
        1731736240,
        1732401065,
        1732437085,
        1732489688
      ]
    }
  },
  "jo": {
    "apps": {
      "joshuto.desktop": [
        1731697796,
        1731736240,
        1732401065,
        1732437085,
        1732489688
      ]
    }
  },
  "jos": {
    "apps": {
      "joshuto.desktop": [
        1731697759,
        1731697796,
        1731736240,
        1732401065,
        1732489688
      ]
    }
  },
  "josh": {
    "apps": {
      "joshuto.desktop": [
        1731697759,
        1731736240,
        1732401065
      ]
    }
  },
  "m": {
    "apps": {
      "miniplayer.desktop": [
        1732530862,
        1733184777,
        1733422995,
        1733792904,
        1733870155
      ],
      "mpv.desktop": [
        1731624419
      ]
    }
  },
  "mi": {
    "apps": {
      "miniplayer.desktop": [
        1732530862,
        1733184777,
        1733422995,
        1733792904,
        1733870155
      ]
    }
  },
  "min": {
    "apps": {
      "miniplayer.desktop": [
        1732530862,
        1733184777,
        1733422995,
        1733792904,
        1733870155
      ]
    }
  },
  "mini": {
    "apps": {
      "miniplayer.desktop": [
        1732530796,
        1733184777,
        1733422995,
        1733792904,
        1733870155
      ]
    }
  },
  "mp": {
    "apps": {
      "mpv.desktop": [
        1731624419
      ]
    }
  },
  "n": {
    "apps": {
      "ncmpcpp.desktop": [
        1731878572,
        1733184747,
        1733187182,
        1733422991,
        1733792902
      ],
      "nemo.desktop": [
        1732438697,
        1732439431,
        1732440803,
        1732488185,
        1732489685
      ],
      "nm-connection-editor.desktop": [
        1732504062
      ],
      "nwg-look.desktop": [
        1731958267,
        1733162711
      ],
      "org.gnome.Nautilus.desktop": [
        1732438665,
        1732520015,
        1733105711,
        1733162730
      ]
    }
  },
  "na": {
    "apps": {
      "org.gnome.Nautilus.desktop": [
        1732438665,
        1732520015,
        1733105711,
        1733162730
      ]
    }
  },
  "nau": {
    "apps": {
      "org.gnome.Nautilus.desktop": [
        1732438665,
        1732520015,
        1733105711,
        1733162730
      ]
    }
  },
  "nc": {
    "apps": {
      "ncmpcpp.desktop": [
        1731878572,
        1733184747,
        1733187182,
        1733422991,
        1733792902
      ]
    }
  },
  "ncm": {
    "apps": {
      "ncmpcpp.desktop": [
        1731878572,
        1733184747,
        1733187182,
        1733422991,
        1733792902
      ]
    }
  },
  "ne": {
    "apps": {
      "nemo.desktop": [
        1732438697,
        1732439431,
        1732440803,
        1732488185,
        1732489685
      ],
      "nm-connection-editor.desktop": [
        1732504062
      ]
    }
  },
  "nem": {
    "apps": {
      "nemo.desktop": [
        1732438697,
        1732439431,
        1732440803,
        1732488185,
        1732489685
      ]
    }
  },
  "net": {
    "apps": {
      "nm-connection-editor.desktop": [
        1732504062
      ]
    }
  },
  "nw": {
    "apps": {
      "nwg-look.desktop": [
        1731958267,
        1733162711
      ]
    }
  },
  "nwg": {
    "apps": {
      "nwg-look.desktop": [
        1731958267
      ]
    }
  },
  "p": {
    "apps": {
      "com.saivert.pwvucontrol.desktop": [
        1732321377,
        1732330042
      ],
      "org.musicbrainz.Picard.desktop": [
        1732489921
      ]
    }
  },
  "pi": {
    "apps": {
      "org.musicbrainz.Picard.desktop": [
        1732489921
      ]
    }
  },
  "pic": {
    "apps": {
      "org.musicbrainz.Picard.desktop": [
        1732489921
      ]
    }
  },
  "pica": {
    "apps": {
      "org.musicbrainz.Picard.desktop": [
        1732489921
      ]
    }
  },
  "pw": {
    "apps": {
      "com.saivert.pwvucontrol.desktop": [
        1732321377,
        1732330042
      ]
    }
  },
  "q": {
    "apps": {
      "org.qutebrowser.qutebrowser.desktop": [
        1732691221,
        1732962857,
        1733096398,
        1733124502,
        1733336186
      ]
    }
  },
  "qu": {
    "apps": {
      "org.qutebrowser.qutebrowser.desktop": [
        1732691221,
        1732962857,
        1733096398,
        1733124502,
        1733336186
      ]
    }
  },
  "qut": {
    "apps": {
      "org.qutebrowser.qutebrowser.desktop": [
        1732691221,
        1732962857,
        1733096398,
        1733124502,
        1733336186
      ]
    }
  },
  "qute": {
    "apps": {
      "org.qutebrowser.qutebrowser.desktop": [
        1732691221,
        1732962857,
        1733096398,
        1733124502,
        1733336186
      ]
    }
  },
  "s": {
    "apps": {
      "org.gnome.SystemMonitor.desktop": [
        1732528222,
        1732530778,
        1732597778,
        1732608084,
        1732867327
      ],
      "org.rncbc.qpwgraph.desktop": [
        1732044554
      ],
      "slack.desktop": [
        1732254643,
        1732691299,
        1733113901,
        1733191199,
        1733200808
      ]
    }
  },
  "sa": {
    "apps": {
      "org.rncbc.qpwgraph.desktop": [
        1732044554
      ]
    }
  },
  "sl": {
    "apps": {
      "slack.desktop": [
        1732254643,
        1732691299,
        1733113901,
        1733191199,
        1733200808
      ]
    }
  },
  "sla": {
    "apps": {
      "slack.desktop": [
        1732254643,
        1732691299,
        1733113901,
        1733191199,
        1733200808
      ]
    }
  },
  "sy": {
    "apps": {
      "org.gnome.SystemMonitor.desktop": [
        1732528222,
        1732530778,
        1732597778,
        1732608084,
        1732867327
      ]
    }
  },
  "sys": {
    "apps": {
      "org.gnome.SystemMonitor.desktop": [
        1732528222,
        1732530778,
        1732597778,
        1732608084,
        1732867327
      ]
    }
  },
  "t": {
    "apps": {
      "transmission-gtk.desktop": [
        1732437092,
        1733900849
      ]
    }
  },
  "tr": {
    "apps": {
      "transmission-gtk.desktop": [
        1732437092,
        1733900849
      ]
    }
  },
  "tra": {
    "apps": {
      "transmission-gtk.desktop": [
        1732437092,
        1733900849
      ]
    }
  },
  "tran": {
    "apps": {
      "transmission-gtk.desktop": [
        1733900849
      ]
    }
  },
  "v": {
    "apps": {
      "vesktop.desktop": [
        1733864569,
        1733867906,
        1733868105,
        1733880217,
        1733941063
      ]
    }
  },
  "ve": {
    "apps": {
      "vesktop.desktop": [
        1733864569,
        1733867906,
        1733868105,
        1733880217,
        1733941063
      ]
    }
  },
  "ves": {
    "apps": {
      "vesktop.desktop": [
        1733864569,
        1733867906,
        1733868105,
        1733880217,
        1733941063
      ]
    }
  },
  "vesk": {
    "apps": {
      "vesktop.desktop": [
        1733807539,
        1733864569,
        1733867906,
        1733868105,
        1733941063
      ]
    }
  }
}
